gait_metrics/__init__.py
gait_metrics/gait_metrics.py
gait_metrics/model_utils.py
gait_metrics/models.py
gait_metrics/utils.py
gait_metrics-0.1.0.dist-info/METADATA
gait_metrics-0.1.0.dist-info/WHEEL
gait_metrics-0.1.0.dist-info/entry_points.txt
gait_metrics-0.1.0.dist-info/top_level.txt
gait_metrics-0.1.0.dist-info/RECORD
