Metadata-Version: 2.4
Name: gait-metrics
Version: 0.1.0
Summary: A package for analyzing acceleration data to compute gait metrics
Author-email: Yonatan Brand <brand1@mail.tau.ac.il>
Classifier: Programming Language :: Python :: 3
Classifier: Operating System :: OS Independent
Requires-Python: >=3.8
Requires-Dist: numpy>=1.20
Requires-Dist: pandas>=1.3
Requires-Dist: scipy>=1.7
Requires-Dist: torch>=2.0
Requires-Dist: actipy
Requires-Dist: importlib-resources>=5.0
Requires-Dist: requests
